{
  "foundations": {
    "Foundation": {
      "Neutral": {
        "100": {
          "value": "#111110",
          "type": "color"
        },
        "200": {
          "value": "#1C1C1B",
          "type": "color"
        },
        "300": {
          "value": "#30302E",
          "type": "color"
        },
        "400": {
          "value": "#494947",
          "type": "color"
        },
        "500": {
          "value": "#6B6B69",
          "type": "color"
        },
        "600": {
          "value": "#91918F",
          "type": "color"
        },
        "700": {
          "value": "#B9B9B8",
          "type": "color"
        },
        "800": {
          "value": "#E2E2E1",
          "type": "color"
        },
        "900": {
          "value": "#F1F1F1",
          "type": "color"
        },
        "1000": {
          "value": "#F8F8F7",
          "type": "color"
        }
      },
      "Brand": {
        "100": {
          "value": "#090640",
          "type": "color"
        },
        "200": {
          "value": "#110662",
          "type": "color"
        },
        "300": {
          "value": "#221098",
          "type": "color"
        },
        "400": {
          "value": "#371EE1",
          "type": "color"
        },
        "500": {
          "value": "#4D58EB",
          "type": "color"
        },
        "600": {
          "value": "#7588F6",
          "type": "color"
        },
        "700": {
          "value": "#A4B6FB",
          "type": "color"
        },
        "800": {
          "value": "#DAE2FE",
          "type": "color"
        },
        "900": {
          "value": "#ECF1FF",
          "type": "color"
        },
        "1000": {
          "value": "#F6F8FF",
          "type": "color"
        }
      },
      "Accent": {
        "100": {
          "value": "#04140E",
          "type": "color"
        },
        "200": {
          "value": "#0A1F17",
          "type": "color"
        },
        "300": {
          "value": "#16362A",
          "type": "color"
        },
        "400": {
          "value": "#244E3E",
          "type": "color"
        },
        "500": {
          "value": "#38765E",
          "type": "color"
        },
        "600": {
          "value": "#4E9F80",
          "type": "color"
        },
        "700": {
          "value": "#65CBA3",
          "type": "color"
        },
        "800": {
          "value": "#78EBBE",
          "type": "color"
        },
        "900": {
          "value": "#D4F9E8",
          "type": "color"
        },
        "1000": {
          "value": "#ECFBF4",
          "type": "color"
        }
      },
      "Success": {
        "100": {
          "value": "#001505",
          "type": "color"
        },
        "200": {
          "value": "#00210A",
          "type": "color"
        },
        "300": {
          "value": "#003916",
          "type": "color"
        },
        "400": {
          "value": "#005324",
          "type": "color"
        },
        "500": {
          "value": "#057B39",
          "type": "color"
        },
        "600": {
          "value": "#00AF54",
          "type": "color"
        },
        "700": {
          "value": "#76CB8B",
          "type": "color"
        },
        "800": {
          "value": "#CBEAD1",
          "type": "color"
        },
        "900": {
          "value": "#E7F4E9",
          "type": "color"
        },
        "1000": {
          "value": "#F1FAF3",
          "type": "color"
        }
      },
      "Info": {
        "100": {
          "value": "#041318",
          "type": "color"
        },
        "200": {
          "value": "#0C1E24",
          "type": "color"
        },
        "300": {
          "value": "#16343D",
          "type": "color"
        },
        "400": {
          "value": "#254C58",
          "type": "color"
        },
        "500": {
          "value": "#3B7282",
          "type": "color"
        },
        "600": {
          "value": "#519AAF",
          "type": "color"
        },
        "700": {
          "value": "#73D7F4",
          "type": "color"
        },
        "800": {
          "value": "#BAEAFA",
          "type": "color"
        },
        "900": {
          "value": "#DAF5FD",
          "type": "color"
        },
        "1000": {
          "value": "#EFFAFD",
          "type": "color"
        }
      },
      "Warning": {
        "100": {
          "value": "#171000",
          "type": "color"
        },
        "200": {
          "value": "#221B05",
          "type": "color"
        },
        "300": {
          "value": "#3B2F04",
          "type": "color"
        },
        "400": {
          "value": "#54450A",
          "type": "color"
        },
        "500": {
          "value": "#7E6918",
          "type": "color"
        },
        "600": {
          "value": "#AA8E23",
          "type": "color"
        },
        "700": {
          "value": "#D9B62F",
          "type": "color"
        },
        "800": {
          "value": "#FFE176",
          "type": "color"
        },
        "900": {
          "value": "#FFF1BB",
          "type": "color"
        },
        "1000": {
          "value": "#FFF8DD",
          "type": "color"
        }
      },
      "Critical": {
        "100": {
          "value": "#2B0205",
          "type": "color"
        },
        "200": {
          "value": "#400009",
          "type": "color"
        },
        "300": {
          "value": "#680110",
          "type": "color"
        },
        "400": {
          "value": "#92021B",
          "type": "color"
        },
        "500": {
          "value": "#D7002B",
          "type": "color"
        },
        "600": {
          "value": "#FF5257",
          "type": "color"
        },
        "700": {
          "value": "#FDA09A",
          "type": "color"
        },
        "800": {
          "value": "#FDDAD8",
          "type": "color"
        },
        "900": {
          "value": "#FEEDEB",
          "type": "color"
        },
        "1000": {
          "value": "#FFF6F4",
          "type": "color"
        }
      }
    },
    "fontFamilies": {
      "Primary": {
        "value": "DM Sans",
        "type": "fontFamilies"
      },
      "Mono": {
        "value": "DM Mono",
        "type": "fontFamilies"
      },
      "Icons": {
        "value": "Font Awesome 5 Pro",
        "type": "fontFamilies"
      }
    },
    "letterSpacing": {
      "0": {
        "value": "0",
        "type": "letterSpacing"
      },
      "100": {
        "value": "4",
        "type": "letterSpacing"
      },
      "200": {
        "value": "4",
        "type": "letterSpacing"
      },
      "300": {
        "value": "6",
        "type": "letterSpacing"
      }
    },
    "fontWeights": {
      "100": {
        "value": "Thin",
        "type": "fontWeights"
      },
      "200": {
        "value": "Light",
        "type": "fontWeights"
      },
      "300": {
        "value": "Book",
        "type": "fontWeights"
      },
      "400": {
        "value": "Regular",
        "type": "fontWeights"
      },
      "500": {
        "value": "Medium",
        "type": "fontWeights"
      },
      "600": {
        "value": "Semi-Bold",
        "type": "fontWeights"
      },
      "700": {
        "value": "Bold",
        "type": "fontWeights"
      },
      "800": {
        "value": "Extrabold",
        "type": "fontWeights"
      },
      "900": {
        "value": "Black",
        "type": "fontWeights"
      }
    }
  },
  "coloursDark": {
    "Canvas": {
      "Inverse": {
        "value": "{Foundation.Neutral.1000}",
        "type": "color"
      },
      "Default": {
        "value": "{Foundation.Neutral.100}",
        "type": "color"
      }
    },
    "Background": {
      "Default": {
        "value": "{Foundation.Neutral.200}",
        "type": "color"
      },
      "Black": {
        "value": "{Foundation.Neutral.1000}",
        "type": "color"
      }
    },
    "Neutral": {
      "Background": {
        "value": "{Foundation.Neutral.700}",
        "type": "color"
      },
      "Background-Hover": {
        "value": "{Foundation.Neutral.600}",
        "type": "color"
      },
      "Background-Active": {
        "value": "{Foundation.Neutral.800}",
        "type": "color"
      },
      "Background-Disabled": {
        "value": "{Foundation.Neutral.400}",
        "type": "color"
      },
      "Background-Subdued": {
        "value": "{Foundation.Neutral.500}",
        "type": "color"
      },
      "Background-Faint": {
        "value": "{Foundation.Neutral.200}",
        "type": "color"
      },
      "Background-Faint-Hover": {
        "value": "{Foundation.Neutral.300}",
        "type": "color"
      },
      "Background-Faint-Active": {
        "value": "{Foundation.Neutral.400}",
        "type": "color"
      },
      "Background-Faint-Disabled": {
        "value": "{Foundation.Neutral.200}",
        "type": "color"
      },
      "Content": {
        "value": "{Foundation.Neutral.900}",
        "type": "color"
      },
      "Content-Hover": {
        "value": "{Foundation.Neutral.600}",
        "type": "color"
      },
      "Content-Active": {
        "value": "{Foundation.Neutral.800}",
        "type": "color"
      },
      "Content-Disabled": {
        "value": "{Foundation.Neutral.600}",
        "type": "color"
      },
      "Content-Subdued": {
        "value": "{Foundation.Neutral.600}",
        "type": "color"
      },
      "Content-Faint": {
        "value": "{Foundation.Neutral.100}",
        "type": "color"
      },
      "Content-Faint-Hover": {
        "value": "{Foundation.Neutral.300}",
        "type": "color"
      },
      "Content-Faint-Active": {
        "value": "{Foundation.Neutral.400}",
        "type": "color"
      },
      "Content-Faint-Disabled": {
        "value": "{Foundation.Neutral.500}",
        "type": "color"
      },
      "Border": {
        "value": "{Foundation.Neutral.700}",
        "type": "color"
      },
      "Border-Hover": {
        "value": "{Foundation.Neutral.600}",
        "type": "color"
      },
      "Border-Active": {
        "value": "{Foundation.Neutral.800}",
        "type": "color"
      },
      "Border-Disabled": {
        "value": "{Foundation.Neutral.400}",
        "type": "color"
      },
      "Border-Subdued": {
        "value": "{Foundation.Neutral.600}",
        "type": "color"
      },
      "Border-Faint": {
        "value": "{Foundation.Neutral.300}",
        "type": "color"
      },
      "Border-Faint-Hover": {
        "value": "{Foundation.Neutral.400}",
        "type": "color"
      },
      "Border-Faint-Active": {
        "value": "{Foundation.Neutral.500}",
        "type": "color"
      },
      "Border-Faint-Disabled": {
        "value": "{Foundation.Neutral.300}",
        "type": "color"
      }
    },
    "Primary": {
      "Background": {
        "value": "{Foundation.Brand.700}",
        "type": "color"
      },
      "Background-Hover": {
        "value": "{Foundation.Brand.600}",
        "type": "color"
      },
      "Background-Active": {
        "value": "{Foundation.Brand.800}",
        "type": "color"
      },
      "Background-Disabled": {
        "value": "{Foundation.Brand.400}",
        "type": "color"
      },
      "Background-Subdued": {
        "value": "{Foundation.Brand.500}",
        "type": "color"
      },
      "Background-Faint": {
        "value": "{Foundation.Brand.200}",
        "type": "color"
      },
      "Background-Faint-Hover": {
        "value": "{Foundation.Brand.300}",
        "type": "color"
      },
      "Background-Faint-Active": {
        "value": "{Foundation.Brand.400}",
        "type": "color"
      },
      "Background-Faint-Disabled": {
        "value": "{Foundation.Brand.200}",
        "type": "color"
      },
      "Content": {
        "value": "{Foundation.Brand.700}",
        "type": "color"
      },
      "Content-Hover": {
        "value": "{Foundation.Brand.600}",
        "type": "color"
      },
      "Content-Active": {
        "value": "{Foundation.Brand.900}",
        "type": "color"
      },
      "Content-Disabled": {
        "value": "{Foundation.Brand.500}",
        "type": "color"
      },
      "Content-Subdued": {
        "value": "{Foundation.Brand.500}",
        "type": "color"
      },
      "Content-Faint": {
        "value": "{Foundation.Brand.100}",
        "type": "color"
      },
      "Content-Faint-Hover": {
        "value": "{Foundation.Brand.300}",
        "type": "color"
      },
      "Content-Faint-Active": {
        "value": "{Foundation.Brand.400}",
        "type": "color"
      },
      "Content-Faint-Disabled": {
        "value": "{Foundation.Brand.500}",
        "type": "color"
      },
      "Border": {
        "value": "{Foundation.Brand.700}",
        "type": "color"
      },
      "Border-Hover": {
        "value": "{Foundation.Brand.600}",
        "type": "color"
      },
      "Border-Active": {
        "value": "{Foundation.Brand.900}",
        "type": "color"
      },
      "Border-Disabled": {
        "value": "{Foundation.Brand.400}",
        "type": "color"
      },
      "Border-Subdued": {
        "value": "{Foundation.Brand.500}",
        "type": "color"
      },
      "Border-Faint": {
        "value": "{Foundation.Brand.200}",
        "type": "color"
      },
      "Border-Faint-Hover": {
        "value": "{Foundation.Brand.300}",
        "type": "color"
      },
      "Border-Faint-Active": {
        "value": "{Foundation.Brand.400}",
        "type": "color"
      },
      "Border-Faint-Disabled": {
        "value": "{Foundation.Brand.200}",
        "type": "color"
      }
    },
    "Info": {
      "Background": {
        "value": "{Foundation.Info.700}",
        "type": "color"
      },
      "Background-Hover": {
        "value": "{Foundation.Info.600}",
        "type": "color"
      },
      "Background-Active": {
        "value": "{Foundation.Info.800}",
        "type": "color"
      },
      "Background-Disabled": {
        "value": "{Foundation.Info.400}",
        "type": "color"
      },
      "Background-Subdued": {
        "value": "{Foundation.Info.500}",
        "type": "color"
      },
      "Background-Faint": {
        "value": "{Foundation.Info.200}",
        "type": "color"
      },
      "Background-Faint-Hover": {
        "value": "{Foundation.Info.300}",
        "type": "color"
      },
      "Background-Faint-Active": {
        "value": "{Foundation.Info.400}",
        "type": "color"
      },
      "Background-Faint-Disabled": {
        "value": "{Foundation.Info.200}",
        "type": "color"
      },
      "Content": {
        "value": "{Foundation.Info.700}",
        "type": "color"
      },
      "Content-Hover": {
        "value": "{Foundation.Info.600}",
        "type": "color"
      },
      "Content-Active": {
        "value": "{Foundation.Info.800}",
        "type": "color"
      },
      "Content-Disabled": {
        "value": "{Foundation.Info.500}",
        "type": "color"
      },
      "Content-Subdued": {
        "value": "{Foundation.Info.500}",
        "type": "color"
      },
      "Content-Faint": {
        "value": "{Foundation.Info.200}",
        "type": "color"
      },
      "Content-Faint-Hover": {
        "value": "{Foundation.Info.300}",
        "type": "color"
      },
      "Content-Faint-Active": {
        "value": "{Foundation.Info.400}",
        "type": "color"
      },
      "Content-Faint-Disabled": {
        "value": "{Foundation.Info.500}",
        "type": "color"
      },
      "Border": {
        "value": "{Foundation.Info.700}",
        "type": "color"
      },
      "Border-Hover": {
        "value": "{Foundation.Info.600}",
        "type": "color"
      },
      "Border-Active": {
        "value": "{Foundation.Info.800}",
        "type": "color"
      },
      "Border-Disabled": {
        "value": "{Foundation.Info.400}",
        "type": "color"
      },
      "Border-Subdued": {
        "value": "{Foundation.Info.500}",
        "type": "color"
      },
      "Border-Faint": {
        "value": "{Foundation.Info.200}",
        "type": "color"
      },
      "Border-Faint-Hover": {
        "value": "{Foundation.Info.300}",
        "type": "color"
      },
      "Border-Faint-Active": {
        "value": "{Foundation.Info.400}",
        "type": "color"
      },
      "Border-Faint-Disabled": {
        "value": "{Foundation.Info.200}",
        "type": "color"
      }
    },
    "Success": {
      "Background": {
        "value": "{Foundation.Success.700}",
        "type": "color"
      },
      "Background-Hover": {
        "value": "{Foundation.Success.600}",
        "type": "color"
      },
      "Background-Active": {
        "value": "{Foundation.Success.800}",
        "type": "color"
      },
      "Background-Disabled": {
        "value": "{Foundation.Success.400}",
        "type": "color"
      },
      "Background-Subdued": {
        "value": "{Foundation.Success.500}",
        "type": "color"
      },
      "Background-Faint": {
        "value": "{Foundation.Success.200}",
        "type": "color"
      },
      "Background-Faint-Hover": {
        "value": "{Foundation.Success.300}",
        "type": "color"
      },
      "Background-Faint-Active": {
        "value": "{Foundation.Success.400}",
        "type": "color"
      },
      "Background-Faint-Disabled": {
        "value": "{Foundation.Success.200}",
        "type": "color"
      },
      "Content": {
        "value": "{Foundation.Success.700}",
        "type": "color"
      },
      "Content-Hover": {
        "value": "{Foundation.Success.600}",
        "type": "color"
      },
      "Content-Active": {
        "value": "{Foundation.Success.800}",
        "type": "color"
      },
      "Content-Disabled": {
        "value": "{Foundation.Success.500}",
        "type": "color"
      },
      "Content-Subdued": {
        "value": "{Foundation.Success.500}",
        "type": "color"
      },
      "Content-Faint": {
        "value": "{Foundation.Success.100}",
        "type": "color"
      },
      "Content-Faint-Hover": {
        "value": "{Foundation.Success.300}",
        "type": "color"
      },
      "Content-Faint-Active": {
        "value": "{Foundation.Success.400}",
        "type": "color"
      },
      "Content-Faint-Disabled": {
        "value": "{Foundation.Success.500}",
        "type": "color"
      },
      "Border": {
        "value": "{Foundation.Success.700}",
        "type": "color"
      },
      "Border-Hover": {
        "value": "{Foundation.Success.600}",
        "type": "color"
      },
      "Border-Active": {
        "value": "{Foundation.Success.800}",
        "type": "color"
      },
      "Border-Disabled": {
        "value": "{Foundation.Success.400}",
        "type": "color"
      },
      "Border-Subdued": {
        "value": "{Foundation.Success.500}",
        "type": "color"
      },
      "Border-Faint": {
        "value": "{Foundation.Success.200}",
        "type": "color"
      },
      "Border-Faint-Hover": {
        "value": "{Foundation.Success.300}",
        "type": "color"
      },
      "Border-Faint-Active": {
        "value": "{Foundation.Success.400}",
        "type": "color"
      },
      "Border-Faint-Disabled": {
        "value": "{Foundation.Success.200}",
        "type": "color"
      }
    },
    "Warning": {
      "Background": {
        "value": "{Foundation.Warning.700}",
        "type": "color"
      },
      "Background-Hover": {
        "value": "{Foundation.Warning.600}",
        "type": "color"
      },
      "Background-Active": {
        "value": "{Foundation.Warning.800}",
        "type": "color"
      },
      "Background-Disabled": {
        "value": "{Foundation.Warning.400}",
        "type": "color"
      },
      "Background-Subdued": {
        "value": "{Foundation.Warning.500}",
        "type": "color"
      },
      "Background-Faint": {
        "value": "{Foundation.Warning.200}",
        "type": "color"
      },
      "Background-Faint-Hover": {
        "value": "{Foundation.Warning.300}",
        "type": "color"
      },
      "Background-Faint-Active": {
        "value": "{Foundation.Warning.400}",
        "type": "color"
      },
      "Background-Faint-Disabled": {
        "value": "{Foundation.Warning.200}",
        "type": "color"
      },
      "Content": {
        "value": "{Foundation.Warning.700}",
        "type": "color"
      },
      "Content-Hover": {
        "value": "{Foundation.Warning.600}",
        "type": "color"
      },
      "Content-Active": {
        "value": "{Foundation.Warning.800}",
        "type": "color"
      },
      "Content-Disabled": {
        "value": "{Foundation.Warning.500}",
        "type": "color"
      },
      "Content-Subdued": {
        "value": "{Foundation.Warning.500}",
        "type": "color"
      },
      "Content-Faint": {
        "value": "{Foundation.Warning.100}",
        "type": "color"
      },
      "Content-Faint-Hover": {
        "value": "{Foundation.Warning.300}",
        "type": "color"
      },
      "Content-Faint-Active": {
        "value": "{Foundation.Warning.400}",
        "type": "color"
      },
      "Content-Faint-Disabled": {
        "value": "{Foundation.Warning.500}",
        "type": "color"
      },
      "Border": {
        "value": "{Foundation.Warning.700}",
        "type": "color"
      },
      "Border-Hover": {
        "value": "{Foundation.Warning.600}",
        "type": "color"
      },
      "Border-Active": {
        "value": "{Foundation.Warning.800}",
        "type": "color"
      },
      "Border-Disabled": {
        "value": "{Foundation.Warning.400}",
        "type": "color"
      },
      "Border-Subdued": {
        "value": "{Foundation.Warning.500}",
        "type": "color"
      },
      "Border-Faint": {
        "value": "{Foundation.Warning.200}",
        "type": "color"
      },
      "Border-Faint-Hover": {
        "value": "{Foundation.Warning.300}",
        "type": "color"
      },
      "Border-aint-Active": {
        "value": "{Foundation.Warning.400}",
        "type": "color"
      },
      "Border-Faint-Disabled": {
        "value": "{Foundation.Warning.200}",
        "type": "color"
      }
    },
    "Critical": {
      "Background": {
        "value": "{Foundation.Critical.700}",
        "type": "color"
      },
      "Background-Hover": {
        "value": "{Foundation.Critical.600}",
        "type": "color"
      },
      "Background-Active": {
        "value": "{Foundation.Critical.800}",
        "type": "color"
      },
      "Background-Disabled": {
        "value": "{Foundation.Critical.400}",
        "type": "color"
      },
      "Background-Subdued": {
        "value": "{Foundation.Critical.500}",
        "type": "color"
      },
      "Background-Faint": {
        "value": "{Foundation.Critical.200}",
        "type": "color"
      },
      "Background-Faint-Hover": {
        "value": "{Foundation.Critical.300}",
        "type": "color"
      },
      "Background-Faint-Active": {
        "value": "{Foundation.Critical.400}",
        "type": "color"
      },
      "Background-Faint-Disabled": {
        "value": "{Foundation.Critical.200}",
        "type": "color"
      },
      "Content": {
        "value": "{Foundation.Critical.700}",
        "type": "color"
      },
      "Content-Hover": {
        "value": "{Foundation.Critical.600}",
        "type": "color"
      },
      "Content-Active": {
        "value": "{Foundation.Critical.800}",
        "type": "color"
      },
      "Content-Disabled": {
        "value": "{Foundation.Critical.500}",
        "type": "color"
      },
      "Content-Subdued": {
        "value": "{Foundation.Critical.500}",
        "type": "color"
      },
      "Content-Faint": {
        "value": "{Foundation.Critical.100}",
        "type": "color"
      },
      "Content-Faint-Hover": {
        "value": "{Foundation.Critical.300}",
        "type": "color"
      },
      "Content-Faint-Active": {
        "value": "{Foundation.Critical.400}",
        "type": "color"
      },
      "Content-Faint-Disabled": {
        "value": "{Foundation.Critical.500}",
        "type": "color"
      },
      "Border": {
        "value": "{Foundation.Critical.700}",
        "type": "color"
      },
      "Border-Hover": {
        "value": "{Foundation.Critical.600}",
        "type": "color"
      },
      "Border-Active": {
        "value": "{Foundation.Critical.800}",
        "type": "color"
      },
      "Border-Disabled": {
        "value": "{Foundation.Critical.400}",
        "type": "color"
      },
      "Border-Subdued": {
        "value": "{Foundation.Critical.500}",
        "type": "color"
      },
      "Border-Faint": {
        "value": "{Foundation.Critical.200}",
        "type": "color"
      },
      "Border-Faint-Hover": {
        "value": "{Foundation.Critical.300}",
        "type": "color"
      },
      "Border-Faint-Active": {
        "value": "{Foundation.Critical.400}",
        "type": "color"
      },
      "Border-Faint-Disabled": {
        "value": "{Foundation.Critical.200}",
        "type": "color"
      }
    }
  },
  "$themes": [
    {
      "id": "6f58fae515b31f346ff414dceff0795884ef5558",
      "name": "CargoWise",
      "selectedTokenSets": {
        "foundations": "enabled",
        "coloursDark": "disabled"
      },
      "$figmaStyleReferences": {}
    }
  ],
  "$metadata": {
    "tokenSetOrder": [
      "foundations",
      "coloursDark"
    ]
  }
}